pulumi_kubernetes_cert_manager/__init__.py
pulumi_kubernetes_cert_manager/_inputs.py
pulumi_kubernetes_cert_manager/_utilities.py
pulumi_kubernetes_cert_manager/cert_manager.py
pulumi_kubernetes_cert_manager/outputs.py
pulumi_kubernetes_cert_manager/provider.py
pulumi_kubernetes_cert_manager/pulumi-plugin.json
pulumi_kubernetes_cert_manager/py.typed
pulumi_kubernetes_cert_manager-0.2.0.dist-info/METADATA
pulumi_kubernetes_cert_manager-0.2.0.dist-info/WHEEL
pulumi_kubernetes_cert_manager-0.2.0.dist-info/top_level.txt
pulumi_kubernetes_cert_manager-0.2.0.dist-info/RECORD
