Metadata-Version: 2.2
Name: pulumi_kubernetes_cert_manager
Version: 0.2.0
Summary: Strongly-typed Cert Manager installation
License: Apache-2.0
Project-URL: Homepage, https://pulumi.io
Project-URL: Repository, https://github.com/pulumi/pulumi-kubernetes-cert-manager
Keywords: pulumi,kubernetes,cert-manager,kind/component,category/infrastructure
Requires-Python: >=3.9
Requires-Dist: parver>=0.2.1
Requires-Dist: pulumi<4.0.0,>=3.142.0
Requires-Dist: pulumi-kubernetes<5.0.0,>=4.0.0
Requires-Dist: semver>=2.8.1
Requires-Dist: typing-extensions>=4.11; python_version < "3.11"
